montecarlo_opentelemetry/__init__.py
montecarlo_opentelemetry/_llm.py
montecarlo_opentelemetry/_setup.py
montecarlo_opentelemetry/_span_processor.py
montecarlo_opentelemetry/_tracing.py
montecarlo_opentelemetry/py.typed
montecarlo_opentelemetry-0.2.0.dist-info/WHEEL
montecarlo_opentelemetry-0.2.0.dist-info/METADATA
montecarlo_opentelemetry-0.2.0.dist-info/RECORD
