Metadata-Version: 2.3
Name: montecarlo-opentelemetry
Version: 0.2.0
Summary: OpenTelemetry SDK for Monte Carlo
Keywords: opentelemetry,monitoring,observability,tracing,telemetry,monte-carlo
Author-email: info@montecarlodata.com
License: Apache-2.0
Classifier: Development Status :: 3 - Alpha
Classifier: Intended Audience :: Developers
Classifier: Natural Language :: English
Classifier: Topic :: Software Development :: Build Tools
Classifier: License :: OSI Approved :: Apache Software License
Classifier: Programming Language :: Python :: 3.10
Classifier: Programming Language :: Python :: 3.11
Classifier: Programming Language :: Python :: 3.12
Classifier: Programming Language :: Python :: 3.13
Requires-Dist: opentelemetry-exporter-otlp>=1.34.0
Requires-Dist: opentelemetry-instrumentation>=0.55b1
Requires-Dist: opentelemetry-instrumentation-threading>=0.55b1
Requires-Dist: opentelemetry-sdk>=1.34.0
Requires-Dist: wrapt>=1.17.2
Maintainer-email: info@montecarlodata.com
Requires-Python: >=3.10
Project-URL: Homepage, https://www.montecarlodata.com
